prompt_functions/__init__.py
prompt_functions/prompt_functions.py
prompt_functions/utils.py
prompt_functions-0.1.27.dist-info/LICENSE
prompt_functions-0.1.27.dist-info/METADATA
prompt_functions-0.1.27.dist-info/WHEEL
prompt_functions-0.1.27.dist-info/RECORD
