Metadata-Version: 2.1
Name: prompt-functions
Version: 0.1.27
Summary: Build semantic functions.
License: MIT
Author: Kasper Junge
Requires-Python: >=3.9,<4.0
Classifier: License :: OSI Approved :: MIT License
Classifier: Programming Language :: Python :: 3
Classifier: Programming Language :: Python :: 3.9
Classifier: Programming Language :: Python :: 3.10
Classifier: Programming Language :: Python :: 3.11
Requires-Dist: aiohttp (>=3.8.5,<4.0.0)
Requires-Dist: asyncio (>=3.4.3,<4.0.0)
Requires-Dist: requests (>=2.31.0,<3.0.0)
